trakt_tools/__init__.py
trakt_tools/core/__init__.py
trakt_tools/core/authentication.py
trakt_tools/core/helpers.py
trakt_tools/core/input.py
trakt_tools/models/__init__.py
trakt_tools/models/backup.py
trakt_tools/models/profile.py
trakt_tools/runner/__init__.py
trakt_tools/runner/main.py
trakt_tools/runner/commands/__init__.py
trakt_tools/runner/commands/history/__init__.py
trakt_tools/runner/commands/history/duplicates/__init__.py
trakt_tools/runner/commands/history/duplicates/merge.py
trakt_tools/runner/commands/history/duplicates/scan.py
trakt_tools/runner/commands/profile/__init__.py
trakt_tools/runner/commands/profile/backup/__init__.py
trakt_tools/runner/commands/profile/backup/apply.py
trakt_tools/runner/commands/profile/backup/create.py
trakt_tools/tasks/__init__.py
trakt_tools/tasks/base.py
trakt_tools/tasks/history/__init__.py
trakt_tools/tasks/history/duplicates/__init__.py
trakt_tools/tasks/history/duplicates/core/__init__.py
trakt_tools/tasks/history/duplicates/core/formatter.py
trakt_tools/tasks/history/duplicates/merge/__init__.py
trakt_tools/tasks/history/duplicates/merge/executor.py
trakt_tools/tasks/history/duplicates/merge/main.py
trakt_tools/tasks/history/duplicates/scan/__init__.py
trakt_tools/tasks/history/duplicates/scan/main.py
trakt_tools/tasks/history/duplicates/scan/models.py
trakt_tools/tasks/profile/__init__.py
trakt_tools/tasks/profile/backup/__init__.py
trakt_tools/tasks/profile/backup/apply/__init__.py
trakt_tools/tasks/profile/backup/apply/main.py
trakt_tools/tasks/profile/backup/apply/handlers/__init__.py
trakt_tools/tasks/profile/backup/apply/handlers/history.py
trakt_tools/tasks/profile/backup/create/__init__.py
trakt_tools/tasks/profile/backup/create/main.py
trakt_tools/tasks/profile/backup/create/handlers/__init__.py
trakt_tools/tasks/profile/backup/create/handlers/collection.py
trakt_tools/tasks/profile/backup/create/handlers/history.py
trakt_tools/tasks/profile/backup/create/handlers/playback.py
trakt_tools-0.2.3.dist-info/AUTHORS
trakt_tools-0.2.3.dist-info/METADATA
trakt_tools-0.2.3.dist-info/WHEEL
trakt_tools-0.2.3.dist-info/entry_points.txt
trakt_tools-0.2.3.dist-info/pbr.json
trakt_tools-0.2.3.dist-info/top_level.txt
trakt_tools-0.2.3.dist-info/RECORD
