Metadata-Version: 2.1
Name: trakt-tools
Version: 0.2.3
Summary: Command-line tools for Trakt.tv.
Home-page: https://github.com/fuzeman/trakt-tools
Author: Dean Gardiner
Author-email: me@dgardiner.net
Keywords: trakt,trakt.tv,tools,utilities
Platform: any
Classifier: Intended Audience :: End Users/Desktop
Classifier: Operating System :: OS Independent
Classifier: Programming Language :: Python
Classifier: Programming Language :: Python :: 2
Classifier: Programming Language :: Python :: 2.7
Classifier: Programming Language :: Python :: 3
Classifier: Programming Language :: Python :: 3.5
Classifier: Programming Language :: Python :: 3.6
Classifier: Programming Language :: Python :: 3.7
Classifier: Programming Language :: Python :: Implementation :: PyPy
Classifier: Topic :: Utilities
License-File: AUTHORS
Requires-Dist: trakt.py (<4.5.0,>=2.12.0)
Requires-Dist: click (<8.2.0,>=6.0)
Requires-Dist: pytz (>=2016.6)
Requires-Dist: six (>=1.10.0)
